codecompanion/__init__.py
codecompanion/core.py
codecompanion-0.1.0.dist-info/licenses/LICENSE
codecompanion-0.1.0.dist-info/METADATA
codecompanion-0.1.0.dist-info/WHEEL
codecompanion-0.1.0.dist-info/top_level.txt
codecompanion-0.1.0.dist-info/RECORD
