Metadata-Version: 2.4
Name: codecompanion
Version: 0.1.0
Summary: Smart code analysis companion for Python developers
Author: Eden Simamora
Author-email: aeden6877@gmail.com
Classifier: Programming Language :: Python :: 3
Classifier: License :: OSI Approved :: MIT License
Classifier: Operating System :: OS Independent
Requires-Python: >=3.6
License-File: LICENSE
Requires-Dist: autopep8
Requires-Dist: pyflakes
Requires-Dist: radon
Requires-Dist: rich
Requires-Dist: typeguard
Requires-Dist: black
Requires-Dist: docstring-parser
Requires-Dist: jedi
Dynamic: author
Dynamic: author-email
Dynamic: classifier
Dynamic: license-file
Dynamic: requires-dist
Dynamic: requires-python
Dynamic: summary
